<?xml version = '1.0' encoding = 'UTF-8'?>
<TableProxyOraclev10g class="oracle.dbtools.crest.model.design.storage.oracle.v10g.TableProxyOraclev10g" name="SIGNALS" id="720FE707-89F7-F213-17BE-8B16EA7CCE3C" directorySegmentName="seg_0">
   <createdBy>Adrian</createdBy>
   <createdTime>2011-08-06 08:50:10 UTC</createdTime>
   <changedBy>Adrian</changedBy>
   <changedTime>2011-08-06 08:50:10 UTC</changedTime>
   <ownerDesignName>model</ownerDesignName>
   <logging>YES</logging>
   <columnProxies>
      <ColumnProxy class="oracle.dbtools.crest.model.design.storage.oracle.v10g.ColumnProxyOraclev10g" name="CREATION_DATE" id="0BC43834-D54E-310C-EE73-0DB84A4FA838">
         <createdBy>Adrian</createdBy>
         <createdTime>2011-08-06 08:50:10 UTC</createdTime>
         <changedBy>Adrian</changedBy>
         <changedTime>2011-08-06 08:50:10 UTC</changedTime>
         <ownerDesignName>model</ownerDesignName>
      </ColumnProxy>
      <ColumnProxy class="oracle.dbtools.crest.model.design.storage.oracle.v10g.ColumnProxyOraclev10g" name="TYPE_CODE" id="0EF93C2F-DDC0-F799-442B-CC1EF386153F">
         <createdBy>Adrian</createdBy>
         <createdTime>2011-08-06 08:50:10 UTC</createdTime>
         <changedBy>Adrian</changedBy>
         <changedTime>2011-08-06 08:50:10 UTC</changedTime>
         <ownerDesignName>model</ownerDesignName>
      </ColumnProxy>
      <ColumnProxy class="oracle.dbtools.crest.model.design.storage.oracle.v10g.ColumnProxyOraclev10g" name="IS_SENT" id="1178D2CF-BB00-9948-C31E-9FD6ADDDA815">
         <createdBy>Adrian</createdBy>
         <createdTime>2011-08-06 08:50:10 UTC</createdTime>
         <changedBy>Adrian</changedBy>
         <changedTime>2011-08-06 08:50:10 UTC</changedTime>
         <ownerDesignName>model</ownerDesignName>
         <defaultValue>&amp;apos;F&amp;apos;</defaultValue>
      </ColumnProxy>
      <ColumnProxy class="oracle.dbtools.crest.model.design.storage.oracle.v10g.ColumnProxyOraclev10g" name="SIGNAL_ID" id="1C2D5339-FF65-759B-123E-21C0E766CFF9">
         <createdBy>Adrian</createdBy>
         <createdTime>2011-08-06 08:50:10 UTC</createdTime>
         <changedBy>Adrian</changedBy>
         <changedTime>2011-08-06 08:50:10 UTC</changedTime>
         <ownerDesignName>model</ownerDesignName>
      </ColumnProxy>
      <ColumnProxy class="oracle.dbtools.crest.model.design.storage.oracle.v10g.ColumnProxyOraclev10g" name="EMPLOYEE_ID" id="30FD43F4-2624-7C39-8FB3-85571F3A744F">
         <createdBy>Adrian</createdBy>
         <createdTime>2011-08-06 08:50:10 UTC</createdTime>
         <changedBy>Adrian</changedBy>
         <changedTime>2011-08-06 08:50:10 UTC</changedTime>
         <ownerDesignName>model</ownerDesignName>
      </ColumnProxy>
      <ColumnProxy class="oracle.dbtools.crest.model.design.storage.oracle.v10g.ColumnProxyOraclev10g" name="OBJECT_ID" id="B42D2C10-EA8E-D348-4A56-F0351DBF0A8D">
         <createdBy>Adrian</createdBy>
         <createdTime>2011-08-06 08:50:10 UTC</createdTime>
         <changedBy>Adrian</changedBy>
         <changedTime>2011-08-06 08:50:10 UTC</changedTime>
         <ownerDesignName>model</ownerDesignName>
      </ColumnProxy>
      <ColumnProxy class="oracle.dbtools.crest.model.design.storage.oracle.v10g.ColumnProxyOraclev10g" name="ERROR_MESSAGE" id="FB746472-5DA0-D811-E7CA-A5195F8A1CEE">
         <createdBy>Adrian</createdBy>
         <createdTime>2011-08-06 08:50:10 UTC</createdTime>
         <changedBy>Adrian</changedBy>
         <changedTime>2011-08-06 08:50:10 UTC</changedTime>
         <ownerDesignName>model</ownerDesignName>
      </ColumnProxy>
   </columnProxies>
   <primaryKeys>
      <PrimaryKey class="oracle.dbtools.crest.model.design.storage.oracle.v10g.PKProxyOraclev10g" name="SIGNALS_PK" id="CE4F3ED7-02CF-2CF5-F57C-556CD40E4ADD">
         <createdBy>Adrian</createdBy>
         <createdTime>2011-08-06 08:50:10 UTC</createdTime>
         <changedBy>Adrian</changedBy>
         <changedTime>2011-08-06 08:50:10 UTC</changedTime>
         <ownerDesignName>model</ownerDesignName>
         <indexSort>NO</indexSort>
      </PrimaryKey>
   </primaryKeys>
</TableProxyOraclev10g>