<?xml version = '1.0' encoding = 'UTF-8'?>
<Table class="oracle.dbtools.crest.model.design.relational.Table" id="9197D5E5-4B08-9F70-58E6-599FA968BC1A" directorySegmentName="seg_0" name="PRIVILEGE_TYPES">
   <createdBy>Adrian</createdBy>
   <createdTime>2011-06-28 15:16:23 UTC</createdTime>
   <changedBy>Adrian</changedBy>
   <changedTime>2011-06-28 15:16:23 UTC</changedTime>
   <ownerDesignName>model</ownerDesignName>
   <pkName>PRIVILEGE_TYPES_PK</pkName>
   <fonts>
      <FontObject class="oracle.dbtools.crest.model.design.FontObjectWr">
         <foType>Title</foType>
         <fontStyle>1</fontStyle>
         <colorRGB>-16776961</colorRGB>
      </FontObject>
      <FontObject class="oracle.dbtools.crest.model.design.FontObjectWr">
         <foType>Column</foType>
         <colorRGB>-16777216</colorRGB>
      </FontObject>
      <FontObject class="oracle.dbtools.crest.model.design.FontObjectWr">
         <foType>Datatype</foType>
         <colorRGB>-16744448</colorRGB>
      </FontObject>
      <FontObject class="oracle.dbtools.crest.model.design.FontObjectWr">
         <foType>PK Element</foType>
         <colorRGB>-16776961</colorRGB>
      </FontObject>
      <FontObject class="oracle.dbtools.crest.model.design.FontObjectWr">
         <foType>FK Element</foType>
         <colorRGB>-16777216</colorRGB>
      </FontObject>
      <FontObject class="oracle.dbtools.crest.model.design.FontObjectWr">
         <foType>UK Element</foType>
         <colorRGB>-16776961</colorRGB>
      </FontObject>
      <FontObject class="oracle.dbtools.crest.model.design.FontObjectWr">
         <foType>Not Null</foType>
         <colorRGB>-65536</colorRGB>
      </FontObject>
      <FontObject class="oracle.dbtools.crest.model.design.FontObjectWr">
         <foType>Key</foType>
         <colorRGB>-16777216</colorRGB>
      </FontObject>
   </fonts>
   <columns>
      <Column class="oracle.dbtools.crest.model.design.relational.Column" name="PRIVILEGE_CODE" id="30369ED1-62C0-96CD-8DEB-90088C24C57E">
         <createdBy>Adrian</createdBy>
         <createdTime>2011-06-28 15:16:23 UTC</createdTime>
         <changedBy>Adrian</changedBy>
         <changedTime>2011-06-28 15:16:23 UTC</changedTime>
         <ownerDesignName>model</ownerDesignName>
         <use>0</use>
         <logicalDatatype>LOGDT024</logicalDatatype>
         <domain>A7C87971-33EA-3765-286C-2F4F9E5F1A62</domain>
      </Column>
      <Column class="oracle.dbtools.crest.model.design.relational.Column" name="DESCRIPTION" id="60216DEF-05B7-1786-83A5-65C210008E57">
         <createdBy>Adrian</createdBy>
         <createdTime>2011-06-28 15:16:23 UTC</createdTime>
         <changedBy>Adrian</changedBy>
         <changedTime>2011-06-28 15:16:23 UTC</changedTime>
         <ownerDesignName>model</ownerDesignName>
         <use>0</use>
         <logicalDatatype>LOGDT024</logicalDatatype>
         <domain>82EF4F0C-807D-3BCC-902E-6BC747430938</domain>
      </Column>
   </columns>
   <indexes>
      <ind_PK_UK class="oracle.dbtools.crest.model.design.relational.Index" id="D5174A48-6595-CEB6-90FB-054C1675F71E" name="PRIVILEGE_TYPES_PK">
         <createdBy>Adrian</createdBy>
         <createdTime>2011-06-28 15:16:23 UTC</createdTime>
         <changedBy>Adrian</changedBy>
         <changedTime>2011-06-28 15:16:23 UTC</changedTime>
         <ownerDesignName>model</ownerDesignName>
         <pk>true</pk>
         <indexState>Primary Constraint</indexState>
         <indexColumnUsage>
            <colUsage columnID="30369ED1-62C0-96CD-8DEB-90088C24C57E"/>
         </indexColumnUsage>
      </ind_PK_UK>
   </indexes>
</Table>