<?xml version = '1.0' encoding = 'UTF-8'?>
<Entity class="oracle.dbtools.crest.model.design.logical.Entity" id="872E6285-D6A4-20A3-A22D-D6E5E4B589C3" directorySegmentName="seg_0" name="INCIDENTS_HISTORY">
   <createdBy>Adrian</createdBy>
   <createdTime>2011-06-28 15:17:47 UTC</createdTime>
   <changedBy>Adrian</changedBy>
   <changedTime>2011-06-28 15:17:47 UTC</changedTime>
   <commentInRDBMS>Historia incydentów. Przy każdej zmianie stanu incydentu wstawiany jest wiersz do tej tabeli.</commentInRDBMS>
   <generatorID>EB3D726B-DDB4-785E-5E56-3A496DFD5811</generatorID>
   <ownerDesignName>model</ownerDesignName>
   <pkName>INCIDENTS_HISTORY_PK</pkName>
   <adequatelyNormalized>NO</adequatelyNormalized>
   <expectedVolumes>0</expectedVolumes>
   <fwdEngineeringStrategyName>Single Table</fwdEngineeringStrategyName>
   <growthPercent>0</growthPercent>
   <growthType>Year</growthType>
   <maxVolumes>9999999</maxVolumes>
   <minVolumes>0</minVolumes>
   <normalForm>Third</normalForm>
   <fonts>
      <FontObject class="oracle.dbtools.crest.model.design.FontObjectWr">
         <foType>Title</foType>
         <fontStyle>1</fontStyle>
         <colorRGB>-16776961</colorRGB>
      </FontObject>
      <FontObject class="oracle.dbtools.crest.model.design.FontObjectWr">
         <foType>Attribute</foType>
         <colorRGB>-16777216</colorRGB>
      </FontObject>
      <FontObject class="oracle.dbtools.crest.model.design.FontObjectWr">
         <foType>Datatype</foType>
         <colorRGB>-16744448</colorRGB>
      </FontObject>
      <FontObject class="oracle.dbtools.crest.model.design.FontObjectWr">
         <foType>PK Element</foType>
         <colorRGB>-16776961</colorRGB>
      </FontObject>
      <FontObject class="oracle.dbtools.crest.model.design.FontObjectWr">
         <foType>FK Element</foType>
         <colorRGB>-16777216</colorRGB>
      </FontObject>
      <FontObject class="oracle.dbtools.crest.model.design.FontObjectWr">
         <foType>UK Element</foType>
         <colorRGB>-16776961</colorRGB>
      </FontObject>
      <FontObject class="oracle.dbtools.crest.model.design.FontObjectWr">
         <foType>Not Null</foType>
         <colorRGB>-65536</colorRGB>
      </FontObject>
      <FontObject class="oracle.dbtools.crest.model.design.FontObjectWr">
         <foType>Key</foType>
         <colorRGB>-16777216</colorRGB>
      </FontObject>
   </fonts>
   <attributes>
      <Attribute class="oracle.dbtools.crest.model.design.logical.Attribute" name="HISTORY_ID" id="797F27E5-D92A-3421-C5E1-59D44D0313EA">
         <createdBy>Adrian</createdBy>
         <createdTime>2011-06-28 15:17:47 UTC</createdTime>
         <changedBy>Adrian</changedBy>
         <changedTime>2011-06-28 15:17:47 UTC</changedTime>
         <generatorID>DCBF7704-1B9A-84B5-4E50-19A775778BB8</generatorID>
         <ownerDesignName>model</ownerDesignName>
         <use>0</use>
         <logicalDatatype>LOGDT019</logicalDatatype>
         <domain>35F19AF2-2A7C-A1CB-DDB0-0F53B0B00014</domain>
      </Attribute>
      <Attribute class="oracle.dbtools.crest.model.design.logical.Attribute" name="CHANGE_DATE" id="E3388BF4-D440-70C7-3D1D-8DC8E2128A2A">
         <createdBy>Adrian</createdBy>
         <createdTime>2011-06-28 15:17:47 UTC</createdTime>
         <changedBy>Adrian</changedBy>
         <changedTime>2011-06-28 15:17:47 UTC</changedTime>
         <generatorID>9BA266D1-9859-5588-92DC-B9D5A731394C</generatorID>
         <ownerDesignName>model</ownerDesignName>
         <use>0</use>
         <logicalDatatype>LOGDT007</logicalDatatype>
         <domain>61DB3F09-32C4-A3AA-B07A-1F197F669D9F</domain>
      </Attribute>
      <Attribute class="oracle.dbtools.crest.model.design.logical.Attribute" name="EMPLOYEE_ID" id="0A4C87EF-00CF-228E-9E3D-DAE786E89789">
         <createdBy>Adrian</createdBy>
         <createdTime>2011-06-28 15:17:47 UTC</createdTime>
         <changedBy>Adrian</changedBy>
         <changedTime>2011-06-28 15:17:47 UTC</changedTime>
         <generatorID>75786BE5-C188-5DC7-7465-7BA9A0A5483D</generatorID>
         <ownerDesignName>model</ownerDesignName>
         <use>0</use>
         <logicalDatatype>LOGDT019</logicalDatatype>
         <domain>61018E0D-CBB3-8D00-7F35-C7C81D6F7B49</domain>
      </Attribute>
      <Attribute class="oracle.dbtools.crest.model.design.logical.Attribute" name="INCIDENT_ID" id="1FF19ACB-DA1E-FC7A-2116-0AB72377C6DF">
         <createdBy>Adrian</createdBy>
         <createdTime>2011-06-28 15:17:47 UTC</createdTime>
         <changedBy>Adrian</changedBy>
         <changedTime>2011-06-28 15:17:47 UTC</changedTime>
         <ownerDesignName>model</ownerDesignName>
         <use>0</use>
         <logicalDatatype>LOGDT019</logicalDatatype>
         <domain>61018E0D-CBB3-8D00-7F35-C7C81D6F7B49</domain>
         <propertyMap>
            <property name="refers.attribute" value="97A3BAB1-64C3-6E97-AFEF-C78CCC30063E"/>
         </propertyMap>
      </Attribute>
      <Attribute class="oracle.dbtools.crest.model.design.logical.Attribute" name="IMPACT_CODE" id="04CA66FB-2220-58E4-E364-E8D60CB44616">
         <createdBy>Adrian</createdBy>
         <createdTime>2011-06-28 15:17:47 UTC</createdTime>
         <changedBy>Adrian</changedBy>
         <changedTime>2011-06-28 15:17:47 UTC</changedTime>
         <generatorID>9870415B-3E9C-400E-4DD0-0D1BA250A828</generatorID>
         <ownerDesignName>model</ownerDesignName>
         <nullsAllowed>true</nullsAllowed>
         <use>0</use>
         <logicalDatatype>LOGDT025</logicalDatatype>
         <domain>918F5625-4CF5-EF4B-896A-E764AA5E87AF</domain>
      </Attribute>
      <Attribute class="oracle.dbtools.crest.model.design.logical.Attribute" name="URGENCY_CODE" id="CC5BF826-B4AD-88E0-2343-2C05B27DA4AD">
         <createdBy>Adrian</createdBy>
         <createdTime>2011-06-28 15:17:47 UTC</createdTime>
         <changedBy>Adrian</changedBy>
         <changedTime>2011-06-28 15:17:47 UTC</changedTime>
         <generatorID>961FD3DB-A776-75F1-6C0B-00C03083B4BD</generatorID>
         <ownerDesignName>model</ownerDesignName>
         <nullsAllowed>true</nullsAllowed>
         <use>0</use>
         <logicalDatatype>LOGDT025</logicalDatatype>
         <domain>918F5625-4CF5-EF4B-896A-E764AA5E87AF</domain>
      </Attribute>
      <Attribute class="oracle.dbtools.crest.model.design.logical.Attribute" name="STATUS_CODE" id="2EC18889-1B7C-717D-47D6-2C29ADA7227A">
         <createdBy>Adrian</createdBy>
         <createdTime>2011-06-28 15:17:47 UTC</createdTime>
         <changedBy>Adrian</changedBy>
         <changedTime>2011-06-28 15:17:47 UTC</changedTime>
         <generatorID>A44CA3F9-5282-A58C-D9B3-4E36305BCCAD</generatorID>
         <ownerDesignName>model</ownerDesignName>
         <nullsAllowed>true</nullsAllowed>
         <use>0</use>
         <logicalDatatype>LOGDT025</logicalDatatype>
         <domain>918F5625-4CF5-EF4B-896A-E764AA5E87AF</domain>
      </Attribute>
      <Attribute class="oracle.dbtools.crest.model.design.logical.Attribute" name="REVIEW" id="26F4FB0D-C4F7-D3B9-1732-56756201CD39">
         <createdBy>Adrian</createdBy>
         <createdTime>2011-06-28 15:17:47 UTC</createdTime>
         <changedBy>Adrian</changedBy>
         <changedTime>2011-06-28 15:17:47 UTC</changedTime>
         <generatorID>B9B4F503-97A7-FC6B-E92B-00BD3D8A397F</generatorID>
         <ownerDesignName>model</ownerDesignName>
         <nullsAllowed>true</nullsAllowed>
         <use>0</use>
         <logicalDatatype>LOGDT024</logicalDatatype>
         <domain>7B72AFC6-07E9-BB60-8190-AA22330A7E0C</domain>
      </Attribute>
      <Attribute class="oracle.dbtools.crest.model.design.logical.Attribute" name="PRIORITY_CODE" id="3BC37536-A9F6-1B29-5D2E-CC18A996ECF3">
         <createdBy>Adrian</createdBy>
         <createdTime>2011-06-28 15:17:47 UTC</createdTime>
         <changedBy>Adrian</changedBy>
         <changedTime>2011-06-28 15:17:47 UTC</changedTime>
         <generatorID>3569C906-8D96-8FD3-7088-F5201AECD378</generatorID>
         <ownerDesignName>model</ownerDesignName>
         <nullsAllowed>true</nullsAllowed>
         <use>0</use>
         <logicalDatatype>LOGDT025</logicalDatatype>
         <domain>918F5625-4CF5-EF4B-896A-E764AA5E87AF</domain>
      </Attribute>
      <Attribute class="oracle.dbtools.crest.model.design.logical.Attribute" name="CATEGORY_CODE" id="84FFC918-FFD2-2096-9910-7EA15A2EC93C">
         <createdBy>Adrian</createdBy>
         <createdTime>2011-06-28 15:17:47 UTC</createdTime>
         <changedBy>Adrian</changedBy>
         <changedTime>2011-06-28 15:17:47 UTC</changedTime>
         <generatorID>434CFFD9-FD65-3D4B-11B5-BBFD8D9F703E</generatorID>
         <ownerDesignName>model</ownerDesignName>
         <nullsAllowed>true</nullsAllowed>
         <use>0</use>
         <logicalDatatype>LOGDT025</logicalDatatype>
         <domain>918F5625-4CF5-EF4B-896A-E764AA5E87AF</domain>
      </Attribute>
      <Attribute class="oracle.dbtools.crest.model.design.logical.Attribute" name="SUBJECT" id="159BCFAA-D892-5B4B-158F-9A8D1848AB85">
         <createdBy>Adrian</createdBy>
         <createdTime>2011-06-28 15:17:47 UTC</createdTime>
         <changedBy>Adrian</changedBy>
         <changedTime>2011-06-28 15:17:47 UTC</changedTime>
         <generatorID>4AB48D1D-7B73-E128-8EE3-3698814D77BF</generatorID>
         <ownerDesignName>model</ownerDesignName>
         <nullsAllowed>true</nullsAllowed>
         <use>0</use>
         <logicalDatatype>LOGDT024</logicalDatatype>
         <domain>DD4139DC-BA1B-69C3-31D1-EB30511397BF</domain>
      </Attribute>
      <Attribute class="oracle.dbtools.crest.model.design.logical.Attribute" name="DESCRIPTION" id="39054ABF-18FF-1C23-7FCC-54A87AC24CA0">
         <createdBy>Adrian</createdBy>
         <createdTime>2011-06-28 15:17:47 UTC</createdTime>
         <changedBy>Adrian</changedBy>
         <changedTime>2011-06-28 15:17:47 UTC</changedTime>
         <generatorID>11263398-FC3A-FD70-538F-73DB7FCC3063</generatorID>
         <ownerDesignName>model</ownerDesignName>
         <nullsAllowed>true</nullsAllowed>
         <use>0</use>
         <logicalDatatype>LOGDT024</logicalDatatype>
         <domain>5D0F6BAD-C4E1-D760-40ED-AD1B8C3704B6</domain>
      </Attribute>
      <Attribute class="oracle.dbtools.crest.model.design.logical.Attribute" name="STAFF_MEMBER" id="6705206E-4009-FABF-2D4F-632127B8630B">
         <createdBy>Adrian</createdBy>
         <createdTime>2011-06-28 15:17:47 UTC</createdTime>
         <changedBy>Adrian</changedBy>
         <changedTime>2011-06-28 15:17:47 UTC</changedTime>
         <generatorID>A0768642-AAD3-E951-B578-3F96E7EA959B</generatorID>
         <ownerDesignName>model</ownerDesignName>
         <nullsAllowed>true</nullsAllowed>
         <use>0</use>
         <logicalDatatype>LOGDT019</logicalDatatype>
         <domain>61018E0D-CBB3-8D00-7F35-C7C81D6F7B49</domain>
      </Attribute>
      <Attribute class="oracle.dbtools.crest.model.design.logical.Attribute" name="RESOLUTION" id="A3644EDD-279D-B551-439B-420B681799D3">
         <createdBy>Adrian</createdBy>
         <createdTime>2011-06-28 15:17:47 UTC</createdTime>
         <changedBy>Adrian</changedBy>
         <changedTime>2011-06-28 15:17:47 UTC</changedTime>
         <generatorID>29148043-CF1E-5ECC-780B-D65B1B5185DF</generatorID>
         <ownerDesignName>model</ownerDesignName>
         <nullsAllowed>true</nullsAllowed>
         <use>0</use>
         <logicalDatatype>LOGDT024</logicalDatatype>
         <domain>5D0F6BAD-C4E1-D760-40ED-AD1B8C3704B6</domain>
      </Attribute>
      <Attribute class="oracle.dbtools.crest.model.design.logical.Attribute" name="SOURCE_CODE" id="109A10D1-4D45-6735-A879-3A867A708373">
         <createdBy>Adrian</createdBy>
         <createdTime>2011-06-28 15:17:47 UTC</createdTime>
         <changedBy>Adrian</changedBy>
         <changedTime>2011-06-28 15:17:47 UTC</changedTime>
         <generatorID>E5713B81-7F5F-052E-7A7A-D186F7AA44BA</generatorID>
         <ownerDesignName>model</ownerDesignName>
         <nullsAllowed>true</nullsAllowed>
         <use>0</use>
         <logicalDatatype>LOGDT025</logicalDatatype>
         <domain>918F5625-4CF5-EF4B-896A-E764AA5E87AF</domain>
      </Attribute>
      <Attribute class="oracle.dbtools.crest.model.design.logical.Attribute" name="RESOLUTION_DATE" id="C990F841-5460-7E0E-920B-1A55F25491DB">
         <createdBy>Adrian</createdBy>
         <createdTime>2011-06-28 15:17:47 UTC</createdTime>
         <changedBy>Adrian</changedBy>
         <changedTime>2011-06-28 15:17:47 UTC</changedTime>
         <generatorID>FBBF8B91-6EC1-E08B-A991-443702FF5CE1</generatorID>
         <ownerDesignName>model</ownerDesignName>
         <nullsAllowed>true</nullsAllowed>
         <use>0</use>
         <logicalDatatype>LOGDT007</logicalDatatype>
         <domain>61DB3F09-32C4-A3AA-B07A-1F197F669D9F</domain>
      </Attribute>
      <Attribute class="oracle.dbtools.crest.model.design.logical.Attribute" name="GROUP_ID" id="1F8D9459-B146-FA1F-0640-BC1F139861D4">
         <createdBy>Adrian</createdBy>
         <createdTime>2011-06-28 15:17:47 UTC</createdTime>
         <changedBy>Adrian</changedBy>
         <changedTime>2011-06-28 15:17:47 UTC</changedTime>
         <generatorID>B16D0FDE-D689-D5F3-2352-5AB0F3F4D415</generatorID>
         <ownerDesignName>model</ownerDesignName>
         <nullsAllowed>true</nullsAllowed>
         <use>0</use>
         <logicalDatatype>LOGDT019</logicalDatatype>
         <domain>61018E0D-CBB3-8D00-7F35-C7C81D6F7B49</domain>
      </Attribute>
      <Attribute class="oracle.dbtools.crest.model.design.logical.Attribute" name="TARGET_RESOLUTION_DATE" id="C83BED34-6A9E-1AD1-FB7E-BBD718D48821">
         <createdBy>Adrian</createdBy>
         <createdTime>2011-06-28 15:17:47 UTC</createdTime>
         <changedBy>Adrian</changedBy>
         <changedTime>2011-06-28 15:17:47 UTC</changedTime>
         <generatorID>6C88EC92-05D9-B112-03BA-46FEE2E6D80E</generatorID>
         <ownerDesignName>model</ownerDesignName>
         <nullsAllowed>true</nullsAllowed>
         <use>0</use>
         <logicalDatatype>LOGDT007</logicalDatatype>
         <domain>61DB3F09-32C4-A3AA-B07A-1F197F669D9F</domain>
      </Attribute>
      <Attribute class="oracle.dbtools.crest.model.design.logical.Attribute" name="CLOSURE_DATE" id="938E00D9-3FAA-E98D-2CCC-6B69DFF5EF18">
         <createdBy>Adrian</createdBy>
         <createdTime>2011-06-28 15:17:47 UTC</createdTime>
         <changedBy>Adrian</changedBy>
         <changedTime>2011-06-28 15:17:47 UTC</changedTime>
         <generatorID>AEFD3702-EE49-0FF9-4FA4-973290BA1A0F</generatorID>
         <ownerDesignName>model</ownerDesignName>
         <nullsAllowed>true</nullsAllowed>
         <use>0</use>
         <logicalDatatype>LOGDT007</logicalDatatype>
         <domain>61DB3F09-32C4-A3AA-B07A-1F197F669D9F</domain>
      </Attribute>
      <Attribute class="oracle.dbtools.crest.model.design.logical.Attribute" name="SERVICE_ID" id="D9F8D00D-A79D-359B-CF9D-F0502CD60B37">
         <createdBy>Adrian</createdBy>
         <createdTime>2011-06-28 15:17:47 UTC</createdTime>
         <changedBy>Adrian</changedBy>
         <changedTime>2011-06-28 15:17:47 UTC</changedTime>
         <generatorID>CF753D3D-CDFD-31C4-F0E9-D7B438A252F5</generatorID>
         <ownerDesignName>model</ownerDesignName>
         <nullsAllowed>true</nullsAllowed>
         <use>0</use>
         <logicalDatatype>LOGDT019</logicalDatatype>
         <domain>61018E0D-CBB3-8D00-7F35-C7C81D6F7B49</domain>
      </Attribute>
   </attributes>
   <identifiers>
      <identifier class="oracle.dbtools.crest.model.design.logical.CandidateKey" id="6BF74335-BA8D-AF6E-8419-42F88DDF5B78" name="INCIDENTS_HISTORY_PK">
         <createdBy>Adrian</createdBy>
         <createdTime>2011-06-28 15:17:47 UTC</createdTime>
         <changedBy>Adrian</changedBy>
         <changedTime>2011-06-28 15:17:47 UTC</changedTime>
         <generatorID>301A1A87-3344-CFE5-58B3-FF0EB16A3502</generatorID>
         <ownerDesignName>model</ownerDesignName>
         <pk>true</pk>
         <usedAttributes>
            <attributeRef>797F27E5-D92A-3421-C5E1-59D44D0313EA</attributeRef>
         </usedAttributes>
      </identifier>
   </identifiers>
</Entity>