<?xml version = '1.0' encoding = 'UTF-8'?>
<FKIndexAssociation class="oracle.dbtools.crest.model.design.relational.FKIndexAssociation" id="43737A1D-060B-DE50-F737-16C748D15DF1" directorySegmentName="seg_1" name="INCIDENT_CATEGORY_INCIDEN_FK1">
   <createdBy>Adrian</createdBy>
   <createdTime>2011-06-28 15:16:24 UTC</createdTime>
   <changedBy>Adrian</changedBy>
   <changedTime>2011-06-28 15:16:24 UTC</changedTime>
   <ownerDesignName>model</ownerDesignName>
   <containerWithKeyObject>A309D9CE-FA20-344D-D10D-09D3806221F6</containerWithKeyObject>
   <deleteRule>RESTRICT</deleteRule>
   <localFKIndex>ECD0CCC5-9E66-4DF1-070B-66C1AD1E31E5</localFKIndex>
   <keyObject>517E2241-1812-6784-33C2-CA9DF16EBB5B</keyObject>
   <mandatory>false</mandatory>
   <transferable>true</transferable>
</FKIndexAssociation>